mailtrap/__init__.py
mailtrap/client.py
mailtrap/exceptions.py
mailtrap/mail/__init__.py
mailtrap/mail/address.py
mailtrap/mail/attachment.py
mailtrap/mail/base.py
mailtrap/mail/base_entity.py
mailtrap/mail/from_template.py
mailtrap/mail/mail.py
mailtrap_unofficial_async-3.0.0.dist-info/LICENSE.txt
mailtrap_unofficial_async-3.0.0.dist-info/METADATA
mailtrap_unofficial_async-3.0.0.dist-info/WHEEL
mailtrap_unofficial_async-3.0.0.dist-info/top_level.txt
mailtrap_unofficial_async-3.0.0.dist-info/RECORD
