Metadata-Version: 2.1
Name: mailtrap-unofficial-async
Version: 3.0.0
Summary:  Async fork of Official mailtrap.io Python client
Author-email: Railsware Products Studio LLC <support@mailtrap.io>
License: The MIT License (MIT)
Project-URL: Homepage, https://mailtrap.io/
Project-URL: Documentation, https://github.com/TomFaulkner/mailtrap-python
Project-URL: Repository, https://github.com/TomFaulkner/mailtrap-python.git
Project-URL: API documentation, https://api-docs.mailtrap.io/
Classifier: License :: OSI Approved :: MIT License
Classifier: Operating System :: OS Independent
Classifier: Topic :: Software Development :: Libraries :: Application Frameworks
Classifier: Programming Language :: Python :: 3
Classifier: Programming Language :: Python :: 3.10
Classifier: Programming Language :: Python :: 3.11
Classifier: Programming Language :: Python :: 3.12
Classifier: Programming Language :: Python :: 3.13
Requires-Python: >=3.10
License-File: LICENSE.txt
Requires-Dist: httpx>=0.20.0
